Workbook

Sheet Brief
A2: Finance agent workshop
A4: Field | B4: Case rules
A5: Company | B5: Meridian Business Services Pvt Ltd (entirely fictional)
A6: Scope | B6: July to September 2026. Operating expenses only.
A7: Currency and basis | B7: INR in whole rupees. Accrual expenses, excluding GST. Not cash flow.
A8: Budget grain | B8: One row per month, department and expense category.
A9: Actuals grain | B9: One journal line per Transaction ID. Different IDs can share a document reference.
A10: Completeness | B10: Expected population: 4 departments x 6 categories x 3 months = 72 budget keys.
A11: Actual coverage | B11: Extract covers all budget keys. An absent valid journal line means zero spend only after completeness checks. Blank amounts are unknown.
A12: Authorized cleaning | B12: Remove only exact duplicate rows with the same Transaction ID. Keep one and log removal.
A13: Department mapping | B13: Map Financ to Finance. No other aliases are authorized.
A14: Conflicting IDs | B14: If the same Transaction ID has conflicting values, ask before resolving.
A15: Period cutoff | B15: Include posting months 1-Jul-2026 to 30-Sep-2026 inclusive. Keep out-of-period rows in the reconciliation only.
... A25: Source | B25: Synthetic training data created for this workshop. No real company or personal records.

Sheet Sheet1

Sheet Sheet2

Sheet Budget
A1: Budget ID | B1: Month | C1: Department | D1: Category | E1: Budget INR
A2: B-7-0-0 | B2: 46204 | C2: Sales | D2: Payroll | E2: 1500000
A3: B-7-0-1 | B3: 46204 | C3: Sales | D3: Travel | E3: 200000
A4: B-7-0-2 | B4: 46204 | C4: Sales | D4: Software | E4: 80000
A5: B-7-0-3 | B5: 46204 | C5: Sales | D5: Professional fees | E5: 100000
A6: B-7-0-4 | B6: 46204 | C6: Sales | D6: Training | E6: 50000
A7: B-7-0-5 | B7: 46204 | C7: Sales | D7: Facilities | E7: 180000
A8: B-7-1-0 | B8: 46204 | C8: Marketing | D8: Payroll | E8: 900000
A9: B-7-1-1 | B9: 46204 | C9: Marketing | D9: Travel | E9: 100000
A10: B-7-1-2 | B10: 46204 | C10: Marketing | D10: Software | E10: 120000
A11: B-7-1-3 | B11: 46204 | C11: Marketing | D11: Professional fees | E11: 180000
A12: B-7-1-4 | B12: 46204 | C12: Marketing | D12: Training | E12: 40000
A13: B-7-1-5 | B13: 46204 | C13: Marketing | D13: Facilities | E13: 120000
... A73: B-9-3-5 | B73: 46266 | C73: Finance | D73: Facilities | E73: 100000

Sheet Actuals
A1: Transaction ID | B1: Posting month | C1: Department | D1: Category | E1: Document ref | F1: Description | G1: Actual INR
A2: J-1001 | B2: 46204 | C2: Sales | D2: Payroll | E2: INV-7-0-0 | F2: Monthly expense | G2: 1455000
A3: J-1002 | B3: 46204 | C3: Sales | D3: Travel | E3: INV-7-0-1 | F3: Monthly expense | G3: 208000
A4: J-1003 | B4: 46204 | C4: Sales | D4: Software | E4: INV-7-0-2 | F4: Monthly expense | G4: 82000
A5: J-1004 | B5: 46204 | C5: Sales | D5: Professional fees | E5: INV-7-0-3 | F5: Monthly expense | G5: 97000
A6: J-1005 | B6: 46204 | C6: Sales | D6: Training | E6: INV-7-0-4 | F6: Monthly expense | G6: 52000
A7: J-1006 | B7: 46204 | C7: Sales | D7: Facilities | E7: INV-7-0-5 | F7: Monthly expense | G7: 184000
A8: J-1007 | B8: 46204 | C8: Marketing | D8: Payroll | E8: INV-7-1-0 | F8: Monthly expense | G8: 936000
A9: J-1008 | B9: 46204 | C9: Marketing | D9: Travel | E9: INV-7-1-1 | F9: Monthly expense | G9: 102000
A10: J-1009 | B10: 46204 | C10: Marketing | D10: Software | E10: INV-7-1-2 | F10: Monthly expense | G10: 116000
A11: J-1010 | B11: 46204 | C11: Marketing | D11: Professional fees | E11: INV-7-1-3 | F11: Monthly expense | G11: 187000
A12: J-1011 | B12: 46204 | C12: Marketing | D12: Training | E12: INV-7-1-4 | F12: Monthly expense | G12: 41000
A13: J-1012 | B13: 46204 | C13: Marketing | D13: Facilities | E13: INV-7-1-5 | F13: Monthly expense | G13: 116000
... A47: J-1046 | B47: 46235 | C47: Finance | D47: Professional fees | E47: INV-8-3-3 | F47: Monthly expense | G47: 156000
A48: J-1047 | B48: 46235 | C48: Finance | D48: Training | E48: INV-8-3-4 | F48: Monthly expense
A49: J-1048 | B49: 46235 | C49: Finance | D49: Facilities | E49: INV-8-3-5 | F49: Monthly expense | G49: 97000
A50: J-1049 | B50: 46266 | C50: Sales | D50: Payroll | E50: INV-9-0-0 | F50: Monthly expense | G50: 1530000
A51: J-1050 | B51: 46266 | C51: Sales | D51: Travel | E51: INV-9-0-1 | F51: Monthly expense | G51: 194000
A52: J-1051 | B52: 46266 | C52: Sales | D52: Software | E52: INV-9-0-2 | F52: Monthly expense | G52: 83000
A53: J-1052 | B53: 46266 | C53: Sales | D53: Professional fees | E53: INV-9-0-3 | F53: Monthly expense | G53: 102000
A54: J-1053 | B54: 46266 | C54: Sales | D54: Training | E54: INV-9-0-4 | F54: Monthly expense | G54: 49000
A55: J-1054 | B55: 46266 | C55: Sales | D55: Facilities | E55: INV-9-0-5 | F55: Monthly expense | G55: 187000
A56: J-1055 | B56: 46266 | C56: Marketing | D56: Payroll | E56: INV-9-1-0 | F56: Monthly expense | G56: 873000
A57: J-1056 | B57: 46266 | C57: Marketing | D57: Travel | E57: INV-9-1-1 | F57: Monthly expense | G57: 104000
A58: J-1057 | B58: 46266 | C58: Marketing | D58: Software | E58: INV-9-1-2 | F58: Monthly expense | G58: 122000
A59: J-1058 | B59: 46266 | C59: Marketing | D59: Professional fees | E59: INV-9-1-3 | F59: Monthly expense | G59: 600000
A60: J-1059 | B60: 46266 | C60: Marketing | D60: Training | E60: INV-9-1-4 | F60: Monthly expense | G60: 120000
... A77: J-2003 | B77: 46296 | C77: Sales | D77: Travel | E77: INV-OCT-01 | F77: October customer visit | G77: 90000

Sheet Evidence
A1: Evidence ID | B1: Department | C1: Category | D1: Period | E1: Reference | F1: Source note | G1: Owner
A2: E-01 | B2: Sales | C2: Travel | D2: Aug-2026 | E2: Travel log | F2: Three additional customer visits approved for August. | G2: Sales operations
A3: E-02 | B3: Marketing | C3: Professional fees | D3: Sep-2026 | E3: PO-MKT-091 | F3: One-off product launch agency fee. Budget did not include launch scope. | G3: Marketing director
A4: E-03 | B4: Technology | C4: Software | D4: Sep-2026 | E4: CN-TECH-09 | F4: Supplier credit of INR 50,000 relates to September service levels. | G4: IT procurement
A5: E-04 | B5: Technology | C5: Software | D5: Jul-2026 | E5: INV-7-2-2 | F5: Two legitimate service lines. Different transaction IDs share the same invoice. | G5: IT procurement
A6: E-05 | B6: Finance | C6: Professional fees | D6: Jul-2026 | E6: Engagement update | F6: Part of the planned advisory work moved to October. Underspend is timing-related. | G6: Financial controller
A7: E-06 | B7: Marketing | C7: Training | D7: Sep-2026 | E7: Training register | F7: Unplanned launch training delivered in September. | G7: Marketing director
A8: E-07 | B8: Technology | C8: Software | D8: Aug-2026 | E8: License register | F8: Additional developer licenses were activated in August. No unit-price detail supplied. | G8: IT procurement

Sheet Clarification log
A1: Log ID | B1: Raw cell | C1: Transaction ID | D1: Original | E1: Confirmed INR | F1: Authority | G1: User response
A2: C-01 | B2: Actuals!G48 | C2: J-1047 | D2: Blank | E2: 30000 | F2: User confirmation, 26-Oct-2026 | G2: For this fictional exercise, I confirm that transaction J-1047, Finance / Training / August 2026, has an expense amount of INR 30,000. This is the confirmed ledger value for the missing field. Add it only in your cleaned working data and clarification log. Preserve the original blank in the raw source. Continue with the agreed analysis.

Sheet Clean actuals
A1: Transaction ID | B1: Posting month | C1: Department | D1: Category | E1: Document ref | F1: Description | G1: Actual INR | H1: Raw row | I1: Amount source
A2: J-1001 | B2: 2026-07-01 | C2: Sales | D2: Payroll | E2: INV-7-0-0 | F2: Monthly expense | G2: 1455000 | H2: 2 | I2: Raw source
A3: J-1002 | B3: 2026-07-01 | C3: Sales | D3: Travel | E3: INV-7-0-1 | F3: Monthly expense | G3: 208000 | H3: 3 | I3: Raw source
A4: J-1003 | B4: 2026-07-01 | C4: Sales | D4: Software | E4: INV-7-0-2 | F4: Monthly expense | G4: 82000 | H4: 4 | I4: Raw source
A5: J-1004 | B5: 2026-07-01 | C5: Sales | D5: Professional fees | E5: INV-7-0-3 | F5: Monthly expense | G5: 97000 | H5: 5 | I5: Raw source
A6: J-1005 | B6: 2026-07-01 | C6: Sales | D6: Training | E6: INV-7-0-4 | F6: Monthly expense | G6: 52000 | H6: 6 | I6: Raw source
A7: J-1006 | B7: 2026-07-01 | C7: Sales | D7: Facilities | E7: INV-7-0-5 | F7: Monthly expense | G7: 184000 | H7: 7 | I7: Raw source
A8: J-1007 | B8: 2026-07-01 | C8: Marketing | D8: Payroll | E8: INV-7-1-0 | F8: Monthly expense | G8: 936000 | H8: 8 | I8: Raw source
A9: J-1008 | B9: 2026-07-01 | C9: Marketing | D9: Travel | E9: INV-7-1-1 | F9: Monthly expense | G9: 102000 | H9: 9 | I9: Raw source
A10: J-1009 | B10: 2026-07-01 | C10: Marketing | D10: Software | E10: INV-7-1-2 | F10: Monthly expense | G10: 116000 | H10: 10 | I10: Raw source
A11: J-1010 | B11: 2026-07-01 | C11: Marketing | D11: Professional fees | E11: INV-7-1-3 | F11: Monthly expense | G11: 187000 | H11: 11 | I11: Raw source
A12: J-1011 | B12: 2026-07-01 | C12: Marketing | D12: Training | E12: INV-7-1-4 | F12: Monthly expense | G12: 41000 | H12: 12 | I12: Raw source
A13: J-1012 | B13: 2026-07-01 | C13: Marketing | D13: Facilities | E13: INV-7-1-5 | F13: Monthly expense | G13: 116000 | H13: 13 | I13: Raw source
... A75: J-2002 | B75: 2026-09-01 | C75: Technology | D75: Software | E75: CN-TECH-09 | F75: Supplier service credit | G75: -50000 | H75: 75 | I75: Raw source

Sheet Cleaning log
A1: Raw row | B1: Transaction ID | C1: Action | D1: Original | E1: Working treatment | F1: Authority
A2: 48 | B2: J-1047 | C2: Confirmed amount | D2: Blank | E2: 30000 | F2: Clarification log C-01
A3: 73 | B3: J-1072 | C3: Department mapping | D3: Financ | E3: Finance | F3: Brief row 13
A4: 76 | B4: J-1039 | C4: Duplicate removal | D4: Repeated exact row | E4: Retain Actuals row 40 | F4: Brief row 12
A5: 77 | B5: J-2003 | C5: Period exclusion | D5: 2026-10-01 | E5: Reconciliation only | F5: Brief row 15

Sheet Excluded rows
A1: Raw row | B1: Transaction ID | C1: Reason | D1: INR
A2: 76 | B2: J-1039 | C2: Exact duplicate | D2: 400000
A3: 77 | B3: J-2003 | C3: Out of period | D3: 90000

Sheet Variance analysis
A1: Period | B1: Department | C1: Category | D1: Budget INR | E1: Actual INR | F1: Variance INR | G1: Variance % | H1: Direction | I1: Exception
A2: 2026-07-01 | B2: Sales | C2: Payroll | D2: =Budget!E2 -> 1500000 | E2: =SUMIFS('Clean actuals'!$G$2:$G$75,'Clean actuals'!$B$2:$B$75,A2,'Clean actuals'!$C$2:$C$75,B2,'Clean actuals'!$D$2:$D$75,C2) -> 1455000 | F2: =E2-D2 -> -45000 | G2: =IF(D2=0,"n.a.",F2/D2) -> -0.03 | H2: =IF(F2>0,"Unfavorable",IF(F2<0,"Favorable","On budget")) -> Favorable | I2: =IF(D2=0,IF(E2<>0,"Unbudgeted","On budget"),IF(AND(ABS(F2)>100000,ABS(G2)>10%),"Material","Not material")) -> Not material
A3: 2026-07-01 | B3: Sales | C3: Travel | D3: =Budget!E3 -> 200000 | E3: =SUMIFS('Clean actuals'!$G$2:$G$75,'Clean actuals'!$B$2:$B$75,A3,'Clean actuals'!$C$2:$C$75,B3,'Clean actuals'!$D$2:$D$75,C3) -> 208000 | F3: =E3-D3 -> 8000 | G3: =IF(D3=0,"n.a.",F3/D3) -> 0.04 | H3: =IF(F3>0,"Unfavorable",IF(F3<0,"Favorable","On budget")) -> Unfavorable | I3: =IF(D3=0,IF(E3<>0,"Unbudgeted","On budget"),IF(AND(ABS(F3)>100000,ABS(G3)>10%),"Material","Not material")) -> Not material
A4: 2026-07-01 | B4: Sales | C4: Software | D4: =Budget!E4 -> 80000 | E4: =SUMIFS('Clean actuals'!$G$2:$G$75,'Clean actuals'!$B$2:$B$75,A4,'Clean actuals'!$C$2:$C$75,B4,'Clean actuals'!$D$2:$D$75,C4) -> 82000 | F4: =E4-D4 -> 2000 | G4: =IF(D4=0,"n.a.",F4/D4) -> 0.025 | H4: =IF(F4>0,"Unfavorable",IF(F4<0,"Favorable","On budget")) -> Unfavorable | I4: =IF(D4=0,IF(E4<>0,"Unbudgeted","On budget"),IF(AND(ABS(F4)>100000,ABS(G4)>10%),"Material","Not material")) -> Not material
A5: 2026-07-01 | B5: Sales | C5: Professional fees | D5: =Budget!E5 -> 100000 | E5: =SUMIFS('Clean actuals'!$G$2:$G$75,'Clean actuals'!$B$2:$B$75,A5,'Clean actuals'!$C$2:$C$75,B5,'Clean actuals'!$D$2:$D$75,C5) -> 97000 | F5: =E5-D5 -> -3000 | G5: =IF(D5=0,"n.a.",F5/D5) -> -0.03 | H5: =IF(F5>0,"Unfavorable",IF(F5<0,"Favorable","On budget")) -> Favorable | I5: =IF(D5=0,IF(E5<>0,"Unbudgeted","On budget"),IF(AND(ABS(F5)>100000,ABS(G5)>10%),"Material","Not material")) -> Not material
A6: 2026-07-01 | B6: Sales | C6: Training | D6: =Budget!E6 -> 50000 | E6: =SUMIFS('Clean actuals'!$G$2:$G$75,'Clean actuals'!$B$2:$B$75,A6,'Clean actuals'!$C$2:$C$75,B6,'Clean actuals'!$D$2:$D$75,C6) -> 52000 | F6: =E6-D6 -> 2000 | G6: =IF(D6=0,"n.a.",F6/D6) -> 0.04 | H6: =IF(F6>0,"Unfavorable",IF(F6<0,"Favorable","On budget")) -> Unfavorable | I6: =IF(D6=0,IF(E6<>0,"Unbudgeted","On budget"),IF(AND(ABS(F6)>100000,ABS(G6)>10%),"Material","Not material")) -> Not material
A7: 2026-07-01 | B7: Sales | C7: Facilities | D7: =Budget!E7 -> 180000 | E7: =SUMIFS('Clean actuals'!$G$2:$G$75,'Clean actuals'!$B$2:$B$75,A7,'Clean actuals'!$C$2:$C$75,B7,'Clean actuals'!$D$2:$D$75,C7) -> 184000 | F7: =E7-D7 -> 4000 | G7: =IF(D7=0,"n.a.",F7/D7) -> 0.022222222 | H7: =IF(F7>0,"Unfavorable",IF(F7<0,"Favorable","On budget")) -> Unfavorable | I7: =IF(D7=0,IF(E7<>0,"Unbudgeted","On budget"),IF(AND(ABS(F7)>100000,ABS(G7)>10%),"Material","Not material")) -> Not material
A8: 2026-07-01 | B8: Marketing | C8: Payroll | D8: =Budget!E8 -> 900000 | E8: =SUMIFS('Clean actuals'!$G$2:$G$75,'Clean actuals'!$B$2:$B$75,A8,'Clean actuals'!$C$2:$C$75,B8,'Clean actuals'!$D$2:$D$75,C8) -> 936000 | F8: =E8-D8 -> 36000 | G8: =IF(D8=0,"n.a.",F8/D8) -> 0.04 | H8: =IF(F8>0,"Unfavorable",IF(F8<0,"Favorable","On budget")) -> Unfavorable | I8: =IF(D8=0,IF(E8<>0,"Unbudgeted","On budget"),IF(AND(ABS(F8)>100000,ABS(G8)>10%),"Material","Not material")) -> Not material
A9: 2026-07-01 | B9: Marketing | C9: Travel | D9: =Budget!E9 -> 100000 | E9: =SUMIFS('Clean actuals'!$G$2:$G$75,'Clean actuals'!$B$2:$B$75,A9,'Clean actuals'!$C$2:$C$75,B9,'Clean actuals'!$D$2:$D$75,C9) -> 102000 | F9: =E9-D9 -> 2000 | G9: =IF(D9=0,"n.a.",F9/D9) -> 0.02 | H9: =IF(F9>0,"Unfavorable",IF(F9<0,"Favorable","On budget")) -> Unfavorable | I9: =IF(D9=0,IF(E9<>0,"Unbudgeted","On budget"),IF(AND(ABS(F9)>100000,ABS(G9)>10%),"Material","Not material")) -> Not material
A10: 2026-07-01 | B10: Marketing | C10: Software | D10: =Budget!E10 -> 120000 | E10: =SUMIFS('Clean actuals'!$G$2:$G$75,'Clean actuals'!$B$2:$B$75,A10,'Clean actuals'!$C$2:$C$75,B10,'Clean actuals'!$D$2:$D$75,C10) -> 116000 | F10: =E10-D10 -> -4000 | G10: =IF(D10=0,"n.a.",F10/D10) -> -0.033333333 | H10: =IF(F10>0,"Unfavorable",IF(F10<0,"Favorable","On budget")) -> Favorable | I10: =IF(D10=0,IF(E10<>0,"Unbudgeted","On budget"),IF(AND(ABS(F10)>100000,ABS(G10)>10%),"Material","Not material")) -> Not material
A11: 2026-07-01 | B11: Marketing | C11: Professional fees | D11: =Budget!E11 -> 180000 | E11: =SUMIFS('Clean actuals'!$G$2:$G$75,'Clean actuals'!$B$2:$B$75,A11,'Clean actuals'!$C$2:$C$75,B11,'Clean actuals'!$D$2:$D$75,C11) -> 187000 | F11: =E11-D11 -> 7000 | G11: =IF(D11=0,"n.a.",F11/D11) -> 0.038888889 | H11: =IF(F11>0,"Unfavorable",IF(F11<0,"Favorable","On budget")) -> Unfavorable | I11: =IF(D11=0,IF(E11<>0,"Unbudgeted","On budget"),IF(AND(ABS(F11)>100000,ABS(G11)>10%),"Material","Not material")) -> Not material
A12: 2026-07-01 | B12: Marketing | C12: Training | D12: =Budget!E12 -> 40000 | E12: =SUMIFS('Clean actuals'!$G$2:$G$75,'Clean actuals'!$B$2:$B$75,A12,'Clean actuals'!$C$2:$C$75,B12,'Clean actuals'!$D$2:$D$75,C12) -> 41000 | F12: =E12-D12 -> 1000 | G12: =IF(D12=0,"n.a.",F12/D12) -> 0.025 | H12: =IF(F12>0,"Unfavorable",IF(F12<0,"Favorable","On budget")) -> Unfavorable | I12: =IF(D12=0,IF(E12<>0,"Unbudgeted","On budget"),IF(AND(ABS(F12)>100000,ABS(G12)>10%),"Material","Not material")) -> Not material
A13: 2026-07-01 | B13: Marketing | C13: Facilities | D13: =Budget!E13 -> 120000 | E13: =SUMIFS('Clean actuals'!$G$2:$G$75,'Clean actuals'!$B$2:$B$75,A13,'Clean actuals'!$C$2:$C$75,B13,'Clean actuals'!$D$2:$D$75,C13) -> 116000 | F13: =E13-D13 -> -4000 | G13: =IF(D13=0,"n.a.",F13/D13) -> -0.033333333 | H13: =IF(F13>0,"Unfavorable",IF(F13<0,"Favorable","On budget")) -> Favorable | I13: =IF(D13=0,IF(E13<>0,"Unbudgeted","On budget"),IF(AND(ABS(F13)>100000,ABS(G13)>10%),"Material","Not material")) -> Not material
... A73: 2026-09-01 | B73: Finance | C73: Facilities | D73: =Budget!E73 -> 100000 | E73: =SUMIFS('Clean actuals'!$G$2:$G$75,'Clean actuals'!$B$2:$B$75,A73,'Clean actuals'!$C$2:$C$75,B73,'Clean actuals'!$D$2:$D$75,C73) -> 104000 | F73: =E73-D73 -> 4000 | G73: =IF(D73=0,"n.a.",F73/D73) -> 0.04 | H73: =IF(F73>0,"Unfavorable",IF(F73<0,"Favorable","On budget")) -> Unfavorable | I73: =IF(D73=0,IF(E73<>0,"Unbudgeted","On budget"),IF(AND(ABS(F73)>100000,ABS(G73)>10%),"Material","Not material")) -> Not material
A74: Jul–Sep 2026 | B74: Sales | C74: Payroll | D74: =SUM(D2,D26,D50) -> 4500000 | E74: =SUM(E2,E26,E50) -> 4545000 | F74: =E74-D74 -> 45000 | G74: =IF(D74=0,"n.a.",F74/D74) -> 0.01 | H74: =IF(F74>0,"Unfavorable",IF(F74<0,"Favorable","On budget")) -> Unfavorable | I74: =IF(D74=0,IF(E74<>0,"Unbudgeted","On budget"),IF(AND(ABS(F74)>100000,ABS(G74)>10%),"Material","Not material")) -> Not material
A75: Jul–Sep 2026 | B75: Sales | C75: Travel | D75: =SUM(D3,D27,D51) -> 600000 | E75: =SUM(E3,E27,E51) -> 742000 | F75: =E75-D75 -> 142000 | G75: =IF(D75=0,"n.a.",F75/D75) -> 0.23666667 | H75: =IF(F75>0,"Unfavorable",IF(F75<0,"Favorable","On budget")) -> Unfavorable | I75: =IF(D75=0,IF(E75<>0,"Unbudgeted","On budget"),IF(AND(ABS(F75)>100000,ABS(G75)>10%),"Material","Not material")) -> Material
A76: Jul–Sep 2026 | B76: Sales | C76: Software | D76: =SUM(D4,D28,D52) -> 240000 | E76: =SUM(E4,E28,E52) -> 243000 | F76: =E76-D76 -> 3000 | G76: =IF(D76=0,"n.a.",F76/D76) -> 0.0125 | H76: =IF(F76>0,"Unfavorable",IF(F76<0,"Favorable","On budget")) -> Unfavorable | I76: =IF(D76=0,IF(E76<>0,"Unbudgeted","On budget"),IF(AND(ABS(F76)>100000,ABS(G76)>10%),"Material","Not material")) -> Not material
A77: Jul–Sep 2026 | B77: Sales | C77: Professional fees | D77: =SUM(D5,D29,D53) -> 300000 | E77: =SUM(E5,E29,E53) -> 303000 | F77: =E77-D77 -> 3000 | G77: =IF(D77=0,"n.a.",F77/D77) -> 0.01 | H77: =IF(F77>0,"Unfavorable",IF(F77<0,"Favorable","On budget")) -> Unfavorable | I77: =IF(D77=0,IF(E77<>0,"Unbudgeted","On budget"),IF(AND(ABS(F77)>100000,ABS(G77)>10%),"Material","Not material")) -> Not material
A78: Jul–Sep 2026 | B78: Sales | C78: Training | D78: =SUM(D6,D30,D54) -> 150000 | E78: =SUM(E6,E30,E54) -> 152000 | F78: =E78-D78 -> 2000 | G78: =IF(D78=0,"n.a.",F78/D78) -> 0.013333333 | H78: =IF(F78>0,"Unfavorable",IF(F78<0,"Favorable","On budget")) -> Unfavorable | I78: =IF(D78=0,IF(E78<>0,"Unbudgeted","On budget"),IF(AND(ABS(F78)>100000,ABS(G78)>10%),"Material","Not material")) -> Not material
A79: Jul–Sep 2026 | B79: Sales | C79: Facilities | D79: =SUM(D7,D31,D55) -> 540000 | E79: =SUM(E7,E31,E55) -> 546000 | F79: =E79-D79 -> 6000 | G79: =IF(D79=0,"n.a.",F79/D79) -> 0.011111111 | H79: =IF(F79>0,"Unfavorable",IF(F79<0,"Favorable","On budget")) -> Unfavorable | I79: =IF(D79=0,IF(E79<>0,"Unbudgeted","On budget"),IF(AND(ABS(F79)>100000,ABS(G79)>10%),"Material","Not material")) -> Not material
A80: Jul–Sep 2026 | B80: Marketing | C80: Payroll | D80: =SUM(D8,D32,D56) -> 2700000 | E80: =SUM(E8,E32,E56) -> 2727000 | F80: =E80-D80 -> 27000 | G80: =IF(D80=0,"n.a.",F80/D80) -> 0.01 | H80: =IF(F80>0,"Unfavorable",IF(F80<0,"Favorable","On budget")) -> Unfavorable | I80: =IF(D80=0,IF(E80<>0,"Unbudgeted","On budget"),IF(AND(ABS(F80)>100000,ABS(G80)>10%),"Material","Not material")) -> Not material
A81: Jul–Sep 2026 | B81: Marketing | C81: Travel | D81: =SUM(D9,D33,D57) -> 300000 | E81: =SUM(E9,E33,E57) -> 303000 | F81: =E81-D81 -> 3000 | G81: =IF(D81=0,"n.a.",F81/D81) -> 0.01 | H81: =IF(F81>0,"Unfavorable",IF(F81<0,"Favorable","On budget")) -> Unfavorable | I81: =IF(D81=0,IF(E81<>0,"Unbudgeted","On budget"),IF(AND(ABS(F81)>100000,ABS(G81)>10%),"Material","Not material")) -> Not material
A82: Jul–Sep 2026 | B82: Marketing | C82: Software | D82: =SUM(D10,D34,D58) -> 360000 | E82: =SUM(E10,E34,E58) -> 363000 | F82: =E82-D82 -> 3000 | G82: =IF(D82=0,"n.a.",F82/D82) -> 0.0083333333 | H82: =IF(F82>0,"Unfavorable",IF(F82<0,"Favorable","On budget")) -> Unfavorable | I82: =IF(D82=0,IF(E82<>0,"Unbudgeted","On budget"),IF(AND(ABS(F82)>100000,ABS(G82)>10%),"Material","Not material")) -> Not material
A83: Jul–Sep 2026 | B83: Marketing | C83: Professional fees | D83: =SUM(D11,D35,D59) -> 540000 | E83: =SUM(E11,E35,E59) -> 971000 | F83: =E83-D83 -> 431000 | G83: =IF(D83=0,"n.a.",F83/D83) -> 0.79814815 | H83: =IF(F83>0,"Unfavorable",IF(F83<0,"Favorable","On budget")) -> Unfavorable | I83: =IF(D83=0,IF(E83<>0,"Unbudgeted","On budget"),IF(AND(ABS(F83)>100000,ABS(G83)>10%),"Material","Not material")) -> Material
A84: Jul–Sep 2026 | B84: Marketing | C84: Training | D84: =SUM(D12,D36,D60) -> 80000 | E84: =SUM(E12,E36,E60) -> 200000 | F84: =E84-D84 -> 120000 | G84: =IF(D84=0,"n.a.",F84/D84) -> 1.5 | H84: =IF(F84>0,"Unfavorable",IF(F84<0,"Favorable","On budget")) -> Unfavorable | I84: =IF(D84=0,IF(E84<>0,"Unbudgeted","On budget"),IF(AND(ABS(F84)>100000,ABS(G84)>10%),"Material","Not material")) -> Material
A85: Jul–Sep 2026 | B85: Marketing | C85: Facilities | D85: =SUM(D13,D37,D61) -> 360000 | E85: =SUM(E13,E37,E61) -> 363000 | F85: =E85-D85 -> 3000 | G85: =IF(D85=0,"n.a.",F85/D85) -> 0.0083333333 | H85: =IF(F85>0,"Unfavorable",IF(F85<0,"Favorable","On budget")) -> Unfavorable | I85: =IF(D85=0,IF(E85<>0,"Unbudgeted","On budget"),IF(AND(ABS(F85)>100000,ABS(G85)>10%),"Material","Not material")) -> Not material
... A97: Jul–Sep 2026 | B97: Finance | C97: Facilities | D97: =SUM(D25,D49,D73) -> 300000 | E97: =SUM(E25,E49,E73) -> 303000 | F97: =E97-D97 -> 3000 | G97: =IF(D97=0,"n.a.",F97/D97) -> 0.01 | H97: =IF(F97>0,"Unfavorable",IF(F97<0,"Favorable","On budget")) -> Unfavorable | I97: =IF(D97=0,IF(E97<>0,"Unbudgeted","On budget"),IF(AND(ABS(F97)>100000,ABS(G97)>10%),"Material","Not material")) -> Not material
A98: Jul–Sep 2026 | B98: Sales | C98: All categories | D98: =SUM(D2,D3,D4,D5,D6,D7,D26,D27,D28,D29,D30,D31,D50,D51,D52,D53,D54,D55) -> 6330000 | E98: =SUM(E2,E3,E4,E5,E6,E7,E26,E27,E28,E29,E30,E31,E50,E51,E52,E53,E54,E55) -> 6531000 | F98: =E98-D98 -> 201000 | G98: =IF(D98=0,"n.a.",F98/D98) -> 0.031753555 | H98: =IF(F98>0,"Unfavorable",IF(F98<0,"Favorable","On budget")) -> Unfavorable | I98: =IF(D98=0,IF(E98<>0,"Unbudgeted","On budget"),IF(AND(ABS(F98)>100000,ABS(G98)>10%),"Material","Not material")) -> Not material
A99: Jul–Sep 2026 | B99: Marketing | C99: All categories | D99: =SUM(D8,D9,D10,D11,D12,D13,D32,D33,D34,D35,D36,D37,D56,D57,D58,D59,D60,D61) -> 4340000 | E99: =SUM(E8,E9,E10,E11,E12,E13,E32,E33,E34,E35,E36,E37,E56,E57,E58,E59,E60,E61) -> 4927000 | F99: =E99-D99 -> 587000 | G99: =IF(D99=0,"n.a.",F99/D99) -> 0.13525346 | H99: =IF(F99>0,"Unfavorable",IF(F99<0,"Favorable","On budget")) -> Unfavorable | I99: =IF(D99=0,IF(E99<>0,"Unbudgeted","On budget"),IF(AND(ABS(F99)>100000,ABS(G99)>10%),"Material","Not material")) -> Material
A100: Jul–Sep 2026 | B100: Technology | C100: All categories | D100: =SUM(D14,D15,D16,D17,D18,D19,D38,D39,D40,D41,D42,D43,D62,D63,D64,D65,D66,D67) -> 9150000 | E100: =SUM(E14,E15,E16,E17,E18,E19,E38,E39,E40,E41,E42,E43,E62,E63,E64,E65,E66,E67) -> 9513000 | F100: =E100-D100 -> 363000 | G100: =IF(D100=0,"n.a.",F100/D100) -> 0.039672131 | H100: =IF(F100>0,"Unfavorable",IF(F100<0,"Favorable","On budget")) -> Unfavorable | I100: =IF(D100=0,IF(E100<>0,"Unbudgeted","On budget"),IF(AND(ABS(F100)>100000,ABS(G100)>10%),"Material","Not material")) -> Not material
A101: Jul–Sep 2026 | B101: Finance | C101: All categories | D101: =SUM(D20,D21,D22,D23,D24,D25,D44,D45,D46,D47,D48,D49,D68,D69,D70,D71,D72,D73) -> 4590000 | E101: =SUM(E20,E21,E22,E23,E24,E25,E44,E45,E46,E47,E48,E49,E68,E69,E70,E71,E72,E73) -> 4540000 | F101: =E101-D101 -> -50000 | G101: =IF(D101=0,"n.a.",F101/D101) -> -0.010893246 | H101: =IF(F101>0,"Unfavorable",IF(F101<0,"Favorable","On budget")) -> Favorable | I101: =IF(D101=0,IF(E101<>0,"Unbudgeted","On budget"),IF(AND(ABS(F101)>100000,ABS(G101)>10%),"Material","Not material")) -> Not material
A102: Jul–Sep 2026 | B102: All departments | C102: All categories | D102: =SUM(D2,D3,D4,D5,D6,D7,D8,D9,D10,D11,D12,D13,D14,D15,D16,D17,D18,D19,D20,D21,D22,D23,D24,D25,D26,D27,D28,D29,D30,D31,D32,D33,D34,D35,D36,D37,D38,D39,D40,D41,D42,D43,D44,D45,D46,D47,D48,D49,D50,D51,D52,D53,D54,D55,D56,D57,D58,D59,D60,D61,D62,D63,D64,D65,D66,D67,D68,D69,D70,D71,D72,D73) -> 24410000 | E102: =SUM(E2,E3,E4,E5,E6,E7,E8,E9,E10,E11,E12,E13,E14,E15,E16,E17,E18,E19,E20,E21,E22,E23,E24,E25,E26,E27,E28,E29,E30,E31,E32,E33,E34,E35,E36,E37,E38,E39,E40,E41,E42,E43,E44,E45,E46,E47,E48,E49,E50,E51,E52,E53,E54,E55,E56,E57,E58,E59,E60,E61,E62,E63,E64,E65,E66,E67,E68,E69,E70,E71,E72,E73) -> 25511000 | F102: =E102-D102 -> 1101000 | G102: =IF(D102=0,"n.a.",F102/D102) -> 0.045104465 | H102: =IF(F102>0,"Unfavorable",IF(F102<0,"Favorable","On budget")) -> Unfavorable | I102: =IF(D102=0,IF(E102<>0,"Unbudgeted","On budget"),IF(AND(ABS(F102)>100000,ABS(G102)>10%),"Material","Not material")) -> Not material

Sheet CFO report
A1: Period / level | B1: Department | C1: Category | D1: Budget INR | E1: Actual INR | F1: Variance INR | G1: Variance % | H1: Assessment
A2: Jul–Sep 2026 | B2: Sales | C2: All categories | D2: ='Variance analysis'!D98 -> 6330000 | E2: ='Variance analysis'!E98 -> 6531000 | F2: ='Variance analysis'!F98 -> 201000 | G2: ='Variance analysis'!G98 -> 0.031753555 | H2: ='Variance analysis'!I98 -> Not material
A3: Jul–Sep 2026 | B3: Marketing | C3: All categories | D3: ='Variance analysis'!D99 -> 4340000 | E3: ='Variance analysis'!E99 -> 4927000 | F3: ='Variance analysis'!F99 -> 587000 | G3: ='Variance analysis'!G99 -> 0.13525346 | H3: ='Variance analysis'!I99 -> Material
A4: Jul–Sep 2026 | B4: Technology | C4: All categories | D4: ='Variance analysis'!D100 -> 9150000 | E4: ='Variance analysis'!E100 -> 9513000 | F4: ='Variance analysis'!F100 -> 363000 | G4: ='Variance analysis'!G100 -> 0.039672131 | H4: ='Variance analysis'!I100 -> Not material
A5: Jul–Sep 2026 | B5: Finance | C5: All categories | D5: ='Variance analysis'!D101 -> 4590000 | E5: ='Variance analysis'!E101 -> 4540000 | F5: ='Variance analysis'!F101 -> -50000 | G5: ='Variance analysis'!G101 -> -0.010893246 | H5: ='Variance analysis'!I101 -> Not material
A6: Jul–Sep 2026 | B6: Total operating expenses | C6: All categories | D6: ='Variance analysis'!D102 -> 24410000 | E6: ='Variance analysis'!E102 -> 25511000 | F6: ='Variance analysis'!F102 -> 1101000 | G6: ='Variance analysis'!G102 -> 0.045104465 | H6: ='Variance analysis'!I102 -> Not material
A7: 2026-08-01 | B7: Sales | C7: Travel | D7: ='Variance analysis'!D27 -> 200000 | E7: ='Variance analysis'!E27 -> 340000 | F7: ='Variance analysis'!F27 -> 140000 | G7: ='Variance analysis'!G27 -> 0.7 | H7: ='Variance analysis'!I27 -> Material
A8: 2026-09-01 | B8: Marketing | C8: Professional fees | D8: ='Variance analysis'!D59 -> 180000 | E8: ='Variance analysis'!E59 -> 600000 | F8: ='Variance analysis'!F59 -> 420000 | G8: ='Variance analysis'!G59 -> 2.3333333 | H8: ='Variance analysis'!I59 -> Material
A9: 2026-09-01 | B9: Marketing | C9: Training | D9: ='Variance analysis'!D60 -> 0 | E9: ='Variance analysis'!E60 -> 120000 | F9: ='Variance analysis'!F60 -> 120000 | G9: ='Variance analysis'!G60 -> n.a. | H9: ='Variance analysis'!I60 -> Unbudgeted
A10: 2026-09-01 | B10: Technology | C10: Software | D10: ='Variance analysis'!D64 -> 300000 | E10: ='Variance analysis'!E64 -> 430000 | F10: ='Variance analysis'!F64 -> 130000 | G10: ='Variance analysis'!G64 -> 0.43333333 | H10: ='Variance analysis'!I64 -> Material
A11: Jul–Sep 2026 | B11: Sales | C11: Travel | D11: ='Variance analysis'!D75 -> 600000 | E11: ='Variance analysis'!E75 -> 742000 | F11: ='Variance analysis'!F75 -> 142000 | G11: ='Variance analysis'!G75 -> 0.23666667 | H11: ='Variance analysis'!I75 -> Material
A12: Jul–Sep 2026 | B12: Marketing | C12: Professional fees | D12: ='Variance analysis'!D83 -> 540000 | E12: ='Variance analysis'!E83 -> 971000 | F12: ='Variance analysis'!F83 -> 431000 | G12: ='Variance analysis'!G83 -> 0.79814815 | H12: ='Variance analysis'!I83 -> Material
A13: Jul–Sep 2026 | B13: Marketing | C13: Training | D13: ='Variance analysis'!D84 -> 80000 | E13: ='Variance analysis'!E84 -> 200000 | F13: ='Variance analysis'!F84 -> 120000 | G13: ='Variance analysis'!G84 -> 1.5 | H13: ='Variance analysis'!I84 -> Material
A14: Jul–Sep 2026 | B14: Technology | C14: Software | D14: ='Variance analysis'!D88 -> 900000 | E14: ='Variance analysis'!E88 -> 1180000 | F14: ='Variance analysis'!F88 -> 280000 | G14: ='Variance analysis'!G88 -> 0.31111111 | H14: ='Variance analysis'!I88 -> Material

Sheet Report notes
A1: Topic | B1: Commentary / limitation
A2: Basis | B2: July–September 2026; INR whole rupees; accrual operating expenses excluding GST. Positive variance is unfavorable.
A3: Confirmed input | B3: J-1047 = INR 30,000 per user confirmation on 26-Oct-2026. Original Actuals!G48 remains blank.
A4: Materiality | B4: Strict AND test: ABS(variance) > INR 100,000 and ABS(variance / budget) > 10%; aggregate first. Zero budget with nonzero actual is Unbudgeted.
A5: Sales Travel / August | B5: E-01: Sales operations reports three additional approved customer visits. This is a source assertion; trip-level cost evidence is not supplied.
A6: Marketing Professional fees / September | B6: E-02: Marketing director attributes the expense to a one-off launch agency fee outside budget scope. Validate scope and approval before future commitments.
A7: Technology Software | B7: E-04 supports both July invoice lines. E-03 supports the September INR 50,000 credit. E-07 attributes August costs to licenses, but no unit-price detail is supplied; do not infer a price/volume split or September cause.
A8: Finance Professional fees / July | B8: E-05 says planned advisory work moved to October; treat the underspend as timing-related per the note, not proven permanent savings.
A9: Marketing Training / September | B9: E-06 says unplanned launch training was delivered. Review launch budgeting and approval with the Marketing director.
A10: Next actions | B10: Sales operations: reconcile visit costs. Marketing director: validate launch fees/training and future scope. IT procurement: reconcile license counts, rates, and credit. Financial controller: check October advisory accrual. Proposed follow-ups only; no messages, journals, or payments initiated.
A11: Traceability | B11: CFO report links to Variance analysis; monthly actuals sum Clean actuals, which retains source row and clarification ID. Raw sheets remain unchanged.

Sheet Reconciliation
A1: Check | B1: Result
A2: Raw Actuals rows | B2: 76
A3: Exact duplicate rows removed | B3: 1
A4: Out-of-period rows excluded | B4: 1
A5: Clean in-period rows | B5: 74
A6: Expected budget keys | B6: 72
A7: Unique budget keys | B7: 72
A8: Covered budget keys | B8: 72
A9: Unmatched actual keys | B9: 0
A10: Missing clean amounts | B10: 0
A11: Raw known amounts (blank excluded) | B11: 25971000
A12: Confirmed missing amount added | B12: 30000
A13: Duplicate amount removed | B13: -400000
... A17: Reconciliation difference | B17: 0
